jd_flask_uploads/__init__.py
jd_flask_uploads/flaks_uploads.py
jd_flask_uploads-0.3.1.dist-info/LICENSE
jd_flask_uploads-0.3.1.dist-info/METADATA
jd_flask_uploads-0.3.1.dist-info/WHEEL
jd_flask_uploads-0.3.1.dist-info/top_level.txt
jd_flask_uploads-0.3.1.dist-info/RECORD
