Metadata-Version: 2.1
Name: jd-flask-uploads
Version: 0.3.1
Summary: replace for flask-uploads
Author-email: wxg001 <wxg001@21cn.com>
License: MIT
Project-URL: Homepage, https://pypi.org/project/jd-flask-uploads/
Project-URL: Bug Tracker, https://pypi.org/project/jd-flask-uploads/
Classifier: Programming Language :: Python :: 3
Classifier: License :: OSI Approved :: MIT License
Classifier: Operating System :: OS Independent
Requires-Python: >=3.7
License-File: LICENSE
Requires-Dist: Flask (>=2.0.0)
